{
    "download": {
        "attribution": {
            "author": "Material",
            "type": "Material"
        },
        "url": "https://fonts.gstatic.com/s/i/materialicons/system_update_alt/v7/24px.svg?download=true"
    },
    "biking": {
        "attribution": {
            "author": "Ionicons",
            "type": "Ionicons"
        },
        "url": "https://unpkg.com/ionicons@5.1.2/dist/svg/bicycle-outline.svg"
    },
    "play": {
        "attribution": {
            "author": "Ionicons",
            "type": "Ionicons"
        },
        "url": "https://unpkg.com/ionicons@5.1.2/dist/svg/caret-forward-outline.svg"
    }
}